autogtest/__init__.py
autogtest/cli.py
autogtest-0.0.3.dist-info/METADATA
autogtest-0.0.3.dist-info/WHEEL
autogtest-0.0.3.dist-info/entry_points.txt
autogtest-0.0.3.dist-info/licenses/LICENSE
autogtest-0.0.3.dist-info/RECORD
