Metadata-Version: 2.4
Name: autogtest
Version: 0.0.3
Summary: generate gmock files
Project-URL: Homepage, https://10-neon.github.io/autogtest/
Project-URL: Repository, https://github.com/10-neon/autogtest
Project-URL: Documentation, https://10-neon.github.io/autogtest/
Author-email: dongyilong <dyl20001223@163.com>
License-File: LICENSE
Keywords: python
Classifier: Intended Audience :: Developers
Classifier: Programming Language :: Python
Classifier: Programming Language :: Python :: 3
Classifier: Programming Language :: Python :: 3.9
Classifier: Programming Language :: Python :: 3.10
Classifier: Programming Language :: Python :: 3.11
Classifier: Programming Language :: Python :: 3.12
Classifier: Programming Language :: Python :: 3.13
Classifier: Topic :: Software Development :: Libraries :: Python Modules
Requires-Python: <4.0,>=3.9
Requires-Dist: cxxheaderparser>=1.5.0
Requires-Dist: jinja2>=3.1.6
Requires-Dist: typer>=0.15.2
